edeta/.ipynb_checkpoints/Untitled-checkpoint.ipynb
edeta/Untitled.ipynb
edeta/__init__.py
edeta/abstract.py
edeta/db.py
edeta/field.py
edeta/manager.py
edeta/utils.py
edeta-0.1.1.dist-info/WHEEL
edeta-0.1.1.dist-info/METADATA
edeta-0.1.1.dist-info/RECORD
