Metadata-Version: 2.1
Name: edeta
Version: 0.1.1
Summary: 
Author: arantesdv
Author-email: arantesdv@me.com
Requires-Python: >=3.9,<4.0
Classifier: Programming Language :: Python :: 3
Classifier: Programming Language :: Python :: 3.9
Requires-Dist: deta (>=1.0.0,<2.0.0)
